RobotTestrailReporter/RobotTestrailReporter.py
RobotTestrailReporter/__init__.py
robotframework_testrail_reporter-0.0.17.dist-info/METADATA
robotframework_testrail_reporter-0.0.17.dist-info/WHEEL
robotframework_testrail_reporter-0.0.17.dist-info/entry_points.txt
robotframework_testrail_reporter-0.0.17.dist-info/top_level.txt
robotframework_testrail_reporter-0.0.17.dist-info/RECORD
